[
    {
        "title": "QMART H\u00c0 \u0110\u00d4NG",
        "link": "https://www.google.com/maps/place/QMART+H%C3%80+%C4%90%C3%94NG/data=!4m7!3m6!1s0x3135ad542d3379e5:0x8f8dd6e774c321e5!8m2!3d20.9605681!4d105.800571!16s%2Fg%2F11fhtwc7_m!19sChIJ5XkzLVStNTER5SHDdOfWjY8?authuser=0&hl=en&rclk=1",
        "main_category": "Supermarket",
        "rating": 4.1,
        "reviews": 202,
        "website": null,
        "phone": "0963 033 021",
        "address": "QMART H\u00c0 \u0110\u00d4NG, T\u1ea7ng 1 CT6 XA LA, 339 \u0111\u01b0\u1eddng, 70B \u0110. C\u1ea7u B\u01b0\u01a1u, T\u00e2n Tri\u1ec1u, H\u00e0 \u0110\u00f4ng, H\u00e0 N\u1ed9i"
    },
    {
        "title": "Tops Market H\u00e0 \u0110\u00f4ng",
        "link": "https://www.google.com/maps/place/Tops+Market+H%C3%A0+%C4%90%C3%B4ng/data=!4m7!3m6!1s0x3135adfc25f7d417:0x1c8ecb2fd27eedc6!8m2!3d20.9790028!4d105.7856875!16s%2Fg%2F11jb3_m6zv!19sChIJF9T3JfytNTERxu1-0i_Ljhw?authuser=0&hl=en&rclk=1",
        "main_category": "Supermarket",
        "rating": 4.2,
        "reviews": 1597,
        "website": "http://topsmarket.vn/",
        "phone": "024 3352 5888",
        "address": "Tops Market H\u00e0 \u0110\u00f4ng, 102 Tr\u1ea7n Ph\u00fa, P. M\u1ed9 Lao, H\u00e0 \u0110\u00f4ng, H\u00e0 N\u1ed9i 12110"
    },
    {
        "title": "WinMart",
        "link": "https://www.google.com/maps/place/WinMart/data=!4m7!3m6!1s0x3135acdaa99e1c87:0xdb6f8b06effd2b24!8m2!3d20.9743358!4d105.7892777!16s%2Fg%2F11bv38cmdr!19sChIJhxyeqdqsNTERJCv97waLb9s?authuser=0&hl=en&rclk=1",
        "main_category": "Supermarket",
        "rating": 4.2,
        "reviews": 1275,
        "website": "http://winmart.vn/",
        "phone": "024 7106 6866",
        "address": "WinMart, T\u1ea7ng 1 nh\u00e0 CT7A, khu \u0111\u00f4 th\u1ecb m\u1edbi, V\u0103n Qu\u00e1n, Y\u00ean Ph\u00fac, H\u00e0 \u0110\u00f4ng, H\u00e0 N\u1ed9i"
    },
    {
        "title": "\u0110\u1ea1i Si\u00eau Th\u1ecb Aeon Mall H\u00e0 \u0110\u00f4ng",
        "link": "https://www.google.com/maps/place/%C4%90%E1%BA%A1i+Si%C3%AAu+Th%E1%BB%8B+Aeon+Mall+H%C3%A0+%C4%90%C3%B4ng/data=!4m7!3m6!1s0x31345350f7e7b659:0x3558ec41596354f2!8m2!3d20.9899497!4d105.7505901!16s%2Fg%2F11vcmtv852!19sChIJWbbn91BTNDER8lRjWUHsWDU?authuser=0&hl=en&rclk=1",
        "main_category": "Hypermarket",
        "rating": 5,
        "reviews": 2,
        "website": null,
        "phone": null,
        "address": "XQQ2+X6 \u0110\u1ea1i Si\u00eau Th\u1ecb Aeon Mall H\u00e0 \u0110\u00f4ng, D\u01b0\u01a1ng N\u1ed9i, H\u00e0 \u0110\u00f4ng, H\u00e0 N\u1ed9i"
    },
    {
        "title": "Si\u00eau Th\u1ecb Co.opmart H\u00e0 N\u1ed9i",
        "link": "https://www.google.com/maps/place/Si%C3%AAu+Th%E1%BB%8B+Co.opmart+H%C3%A0+N%E1%BB%99i/data=!4m7!3m6!1s0x3135adf4b4bc1297:0xaf93994d1f82ce32!8m2!3d20.9827185!4d105.7904626!16s%2Fg%2F11txv84rk6!19sChIJlxK8tPStNTERMs6CH02Zk68?authuser=0&hl=en&rclk=1",
        "main_category": "Supermarket",
        "rating": 4.6,
        "reviews": 143,
        "website": null,
        "phone": "024 6285 3939",
        "address": "Si\u00eau Th\u1ecb Co.opmart H\u00e0 N\u1ed9i, 10 \u0110. Nguy\u1ec5n Tr\u00e3i, Khu \u0111\u00f4 th\u1ecb B\u1eafc H\u00e0, H\u00e0 \u0110\u00f4ng, H\u00e0 N\u1ed9i"
    },
    {
        "title": "Vtq_Mart",
        "link": "https://www.google.com/maps/place/Vtq_Mart/data=!4m7!3m6!1s0x313453215b45e549:0xd419f9f2aea1e77c!8m2!3d20.974454!4d105.7634254!16s%2Fg%2F11h8l4ycfd!19sChIJSeVFWyFTNDERfOehrvL5GdQ?authuser=0&hl=en&rclk=1",
        "main_category": "Store",
        "rating": null,
        "reviews": null,
        "website": null,
        "phone": null,
        "address": "XQF7+Q9M Vtq_Mart, Khu \u0111\u00f4 th\u1ecb V\u0103n Kh\u00ea, H\u00e0 \u0110\u00f4ng, H\u00e0 N\u1ed9i"
    },
    {
        "title": "K-mart Ha Dong",
        "link": "https://www.google.com/maps/place/K-mart+Ha+Dong/data=!4m7!3m6!1s0x313452d698496605:0x7ae02886644596fe!8m2!3d20.9637439!4d105.775761!16s%2Fg%2F11c32n0k0d!19sChIJBWZJmNZSNDER_pZFZIYo4Ho?authuser=0&hl=en&rclk=1",
        "main_category": "Supermarket",
        "rating": 4.4,
        "reviews": 34,
        "website": null,
        "phone": "024 3352 3718",
        "address": "K-mart Ha Dong, H\u00e0 C\u1ea7u, H\u00e0 \u0110\u00f4ng, H\u00e0 N\u1ed9i"
    },
    {
        "title": "CO.OPMART SCA VICTORIA Supermarket",
        "link": "https://www.google.com/maps/place/CO.OPMART+SCA+VICTORIA+Supermarket/data=!4m7!3m6!1s0x3134533a8e1f13c9:0x17b6c34738e89b92!8m2!3d20.9591916!4d105.7679905!16s%2Fg%2F11fnsbrh0j!19sChIJyRMfjjpTNDERkpvoOEfDthc?authuser=0&hl=en&rclk=1",
        "main_category": "Supermarket",
        "rating": 4.4,
        "reviews": 72,
        "website": "http://www.co-opmart.com.vn/",
        "phone": null,
        "address": "CO.OPMART SCA VICTORIA Supermarket, Khu \u0111\u00f4 th\u1ecb V\u0103n Ph\u00fa, H\u00e0 \u0110\u00f4ng, H\u00e0 N\u1ed9i"
    },
    {
        "title": "Duc Thanh Supermarket",
        "link": "https://www.google.com/maps/place/Duc+Thanh+Supermarket/data=!4m7!3m6!1s0x31345321d4b8a4d9:0x9b693faf4657d56b!8m2!3d20.9725549!4d105.758676!16s%2Fg%2F11cjqwv797!19sChIJ2aS41CFTNDERa9VXRq8_aZs?authuser=0&hl=en&rclk=1",
        "main_category": "Supermarket",
        "rating": 4,
        "reviews": 462,
        "website": null,
        "phone": "024 6259 7606",
        "address": "Duc Thanh Supermarket, The Pride, P. T\u1ed1 H\u1eefu, La Kh\u00ea, H\u00e0 \u0110\u00f4ng, H\u00e0 N\u1ed9i"
    },
    {
        "title": "Co.opmart SCA Goldsilk",
        "link": "https://www.google.com/maps/place/Co.opmart+SCA+Goldsilk/data=!4m7!3m6!1s0x3134536a022d4431:0x631805a3d6693500!8m2!3d20.9768063!4d105.7755109!16s%2Fg%2F11j000b41t!19sChIJMUQtAmpTNDERADVp1qMFGGM?authuser=0&hl=en&rclk=1",
        "main_category": "Supermarket",
        "rating": 4.5,
        "reviews": 82,
        "website": "http://co-opmart.com.vn/",
        "phone": "0911 807 875",
        "address": "Co.opmart SCA Goldsilk, S\u1ed1 430 P. C\u1ea7u Am, P, H\u00e0 \u0110\u00f4ng, H\u00e0 N\u1ed9i"
    },
    {
        "title": "Mother And Baby Supermarket",
        "link": "https://www.google.com/maps/place/Mother+And+Baby+Supermarket/data=!4m7!3m6!1s0x31345329c2ecfbc3:0x139632e16b69b72b!8m2!3d20.9691239!4d105.7746291!16s%2Fg%2F1pztlb60q!19sChIJw_vswilTNDERK7dpa-EylhM?authuser=0&hl=en&rclk=1",
        "main_category": "Supermarket",
        "rating": 2,
        "reviews": 2,
        "website": null,
        "phone": "024 6291 1680",
        "address": "Mother And Baby Supermarket, 167, \u0110\u01b0\u1eddng Quang Trung, Ph\u01b0\u1eddng H\u00e0 C\u1ea7u, Qu\u1eadn H\u00e0 \u0110\u00f4ng, P. Quang Trung, H\u00e0 \u0110\u00f4ng, H\u00e0 N\u1ed9i"
    },
    {
        "title": "Si\u00eau Th\u1ecb Qmart",
        "link": "https://www.google.com/maps/place/Si%C3%AAu+Th%E1%BB%8B+Qmart/data=!4m7!3m6!1s0x3135adceecb1864b:0xe5c7400ac0e901d0!8m2!3d20.9786333!4d105.7969369!16s%2Fg%2F11h34l4n75!19sChIJS4ax7M6tNTER0AHpwApAx-U?authuser=0&hl=en&rclk=1",
        "main_category": "Shopping mall",
        "rating": 5,
        "reviews": 3,
        "website": null,
        "phone": null,
        "address": "XQHW+FQ3 Si\u00eau Th\u1ecb Qmart, P. V\u0103n Qu\u00e1n, H\u00e0 \u0110\u00f4ng, H\u00e0 N\u1ed9i"
    },
    {
        "title": "Si\u00eau Th\u1ecb Milida Mart",
        "link": "https://www.google.com/maps/place/Si%C3%AAu+Th%E1%BB%8B+Milida+Mart/data=!4m7!3m6!1s0x3135accb8c26eb5f:0xd01aa29d05e546de!8m2!3d20.9846912!4d105.787163!16s%2Fg%2F11bwkb4bg6!19sChIJX-smjMusNTER3kblBZ2iGtA?authuser=0&hl=en&rclk=1",
        "main_category": "Supermarket",
        "rating": 3.4,
        "reviews": 5,
        "website": null,
        "phone": "0989 864 866",
        "address": "Si\u00eau Th\u1ecb Milida Mart, 47 P. Nguy\u1ec5n V\u0103n L\u1ed9c, L\u00e0ng Vi\u1ec7t ki\u1ec1u Ch\u00e2u \u00c2u, H\u00e0 \u0110\u00f4ng, H\u00e0 N\u1ed9i"
    },
    {
        "title": "Mother And Baby Supermarket",
        "link": "https://www.google.com/maps/place/Mother+And+Baby+Supermarket/data=!4m7!3m6!1s0x3135acc603524245:0x6b7eb5786130da3c!8m2!3d20.9853766!4d105.7940992!16s%2Fg%2F1pztfycl5!19sChIJRUJSA8asNTERPNowYXi1fms?authuser=0&hl=en&rclk=1",
        "main_category": "Supermarket",
        "rating": null,
        "reviews": null,
        "website": null,
        "phone": "024 6291 1680",
        "address": "Mother And Baby Supermarket, 11A, \u0110\u01b0\u1eddng Tr\u1ea7n Ph\u00fa, P. V\u0103n Qu\u00e1n, H\u00e0 \u0110\u00f4ng, H\u00e0 N\u1ed9i"
    },
    {
        "title": "T-Mart supermarket",
        "link": "https://www.google.com/maps/place/T-Mart+supermarket/data=!4m7!3m6!1s0x313452e48a63f7ef:0x9cf6896f6db807fc!8m2!3d20.9638778!4d105.7497564!16s%2Fg%2F11c1w08xj0!19sChIJ7_djiuRSNDER_Ae4bW-J9pw?authuser=0&hl=en&rclk=1",
        "main_category": "Supermarket",
        "rating": 4.4,
        "reviews": 94,
        "website": null,
        "phone": "1900 6446",
        "address": "XP7X+HW2 T-Mart supermarket, Y\u00ean L\u1ed9, H\u00e0 \u0110\u00f4ng, H\u00e0 N\u1ed9i"
    },
    {
        "title": "WinMart+",
        "link": "https://www.google.com/maps/place/WinMart%2B/data=!4m7!3m6!1s0x313452da28823b4d:0x76fc1b797623689!8m2!3d20.9628782!4d105.76808!16s%2Fg%2F11hzx58_2w!19sChIJTTuCKNpSNDERiTZil7fBbwc?authuser=0&hl=en&rclk=1",
        "main_category": "Supermarket",
        "rating": 4,
        "reviews": 48,
        "website": null,
        "phone": "024 7106 6866",
        "address": "WinMart+, 20 P. V\u0103n Ph\u00fa, Ph\u00fa La, H\u00e0 \u0110\u00f4ng, H\u00e0 N\u1ed9i 12122"
    },
    {
        "title": "Duc Thanh Supermarket",
        "link": "https://www.google.com/maps/place/Duc+Thanh+Supermarket/data=!4m7!3m6!1s0x3135ad28a9a35547:0x6454960e94ddebb0!8m2!3d20.9611735!4d105.7937855!16s%2Fg%2F11b7sx5h25!19sChIJR1WjqSitNTERsOvdlA6WVGQ?authuser=0&hl=en&rclk=1",
        "main_category": "Supermarket",
        "rating": 4.2,
        "reviews": 482,
        "website": null,
        "phone": "0904 609 598",
        "address": "XQ6V+FG7 Duc Thanh Supermarket, Khu \u0111\u00f4 th\u1ecb Xa La, H\u00e0 \u0110\u00f4ng, H\u00e0 N\u1ed9i"
    },
    {
        "title": "Aeon Fivimart H\u00e0 \u0110\u00f4ng",
        "link": "https://www.google.com/maps/place/Aeon+Fivimart+H%C3%A0+%C4%90%C3%B4ng/data=!4m7!3m6!1s0x3134532be8ff4341:0xa8f6a7e852deb4b2!8m2!3d20.9724464!4d105.7770284!16s%2Fg%2F1tkny7pn!19sChIJQUP_6CtTNDERsrTeUuin9qg?authuser=0&hl=en&rclk=1",
        "main_category": "Supermarket",
        "rating": 4,
        "reviews": 290,
        "website": null,
        "phone": null,
        "address": "Aeon Fivimart H\u00e0 \u0110\u00f4ng, 8 \u0110. Quang Trung, P. Nguy\u1ec5n Tr\u00e3i, H\u00e0 \u0110\u00f4ng, H\u00e0 N\u1ed9i"
    },
    {
        "title": "Si\u00eau th\u1ecb Green mart",
        "link": "https://www.google.com/maps/place/Si%C3%AAu+th%E1%BB%8B+Green+mart/data=!4m7!3m6!1s0x3134534a6c0407ff:0xe0e62a9998e5d7d4!8m2!3d20.9724393!4d105.7615501!16s%2Fg%2F11v3pg380l!19sChIJ_wcEbEpTNDER1NflmJkq5uA?authuser=0&hl=en&rclk=1",
        "main_category": "Convenience store",
        "rating": null,
        "reviews": null,
        "website": null,
        "phone": null,
        "address": "XQC6+XJF Si\u00eau th\u1ecb Green mart, La Kh\u00ea, H\u00e0 \u0110\u00f4ng, H\u00e0 N\u1ed9i"
    },
    {
        "title": "Si\u00eau th\u1ecb T- Mart",
        "link": "https://www.google.com/maps/place/Si%C3%AAu+th%E1%BB%8B+T-+Mart/data=!4m7!3m6!1s0x3134529534fec127:0x146d394ce17bac8!8m2!3d20.9457689!4d105.7570194!16s%2Fg%2F11f5hnxf6d!19sChIJJ8H-NJVSNDERyLoXzpTTRgE?authuser=0&hl=en&rclk=1",
        "main_category": "Supermarket",
        "rating": 2.8,
        "reviews": 9,
        "website": null,
        "phone": null,
        "address": "WQW4+8R2 Si\u00eau th\u1ecb T- Mart, Ba La, H\u00e0 \u0110\u00f4ng, H\u00e0 N\u1ed9i"
    },
    {
        "title": "SI\u00caU TH\u1eca TB",
        "link": "https://www.google.com/maps/place/SI%C3%8AU+TH%E1%BB%8A+TB/data=!4m7!3m6!1s0x3135ad7931b45f6d:0x819a4508844d9191!8m2!3d20.9814825!4d105.7943942!16s%2Fg%2F11h0bx005_!19sChIJbV-0MXmtNTERkZFNhAhFmoE?authuser=0&hl=en&rclk=1",
        "main_category": "Discount supermarket",
        "rating": null,
        "reviews": null,
        "website": null,
        "phone": "0975 856 266",
        "address": "SI\u00caU TH\u1eca TB, Ng\u00f5 105 Chi\u1ebfn Th\u1eafng, P. V\u0103n Qu\u00e1n, H\u00e0 \u0110\u00f4ng, H\u00e0 N\u1ed9i 100000"
    },
    {
        "title": "Daily Mart",
        "link": "https://www.google.com/maps/place/Daily+Mart/data=!4m7!3m6!1s0x3135ade2172ffa81:0x83d0c283853278f2!8m2!3d20.9864422!4d105.7867713!16s%2Fg%2F11qww8vsn6!19sChIJgfovF-KtNTER8ngyhYPC0IM?authuser=0&hl=en&rclk=1",
        "main_category": "Supermarket",
        "rating": 2.6,
        "reviews": 10,
        "website": "https://sieuthidailymart.vn/",
        "phone": "0904 681 297",
        "address": "Daily Mart, Mulberry Lane Apartment A, t\u1ea7ng 1 to\u00e0 C, P. M\u1ed9 Lao, H\u00e0 \u0110\u00f4ng, H\u00e0 N\u1ed9i 193824"
    },
    {
        "title": "LA Mart",
        "link": "https://www.google.com/maps/place/LA+Mart/data=!4m7!3m6!1s0x3134536bd1c13d01:0x12561917dfd2b9e5!8m2!3d20.9594467!4d105.7671585!16s%2Fg%2F11h2ph5f26!19sChIJAT3B0WtTNDER5bnS3xcZVhI?authuser=0&hl=en&rclk=1",
        "main_category": "Supermarket",
        "rating": 4.8,
        "reviews": 4,
        "website": "https://beefdaily.com.vn/",
        "phone": "1900 088858",
        "address": "LA Mart, SH12 - K1 chung c\u01b0 Kpark, Khu \u0111\u00f4 th\u1ecb V\u0103n Ph\u00fa, H\u00e0 \u0110\u00f4ng, H\u00e0 N\u1ed9i 152260"
    },
    {
        "title": "Kidsplaza 410 Quang Trung",
        "link": "https://www.google.com/maps/place/Kidsplaza+410+Quang+Trung/data=!4m7!3m6!1s0x313452dbee737dc7:0xa189096b299a0f19!8m2!3d20.962674!4d105.7650062!16s%2Fg%2F11c2jzbplz!19sChIJx31z7ttSNDERGQ-aKWsJiaE?authuser=0&hl=en&rclk=1",
        "main_category": "Supermarket",
        "rating": 4.2,
        "reviews": 30,
        "website": "https://map.coccoc.com/map/3110184681363415",
        "phone": "024 3293 9215",
        "address": "Kidsplaza 410 Quang Trung, 410 \u0110. Quang Trung, La Kh\u00ea, H\u00e0 \u0110\u00f4ng, H\u00e0 N\u1ed9i"
    },
    {
        "title": "AEON MaxValu La Casta",
        "link": "https://www.google.com/maps/place/AEON+MaxValu+La+Casta/data=!4m7!3m6!1s0x3134539056c504ad:0x20ceeee3cdace319!8m2!3d20.9596163!4d105.7664648!16s%2Fg%2F11tf2qyf_f!19sChIJrQTFVpBTNDERGeOszePuziA?authuser=0&hl=en&rclk=1",
        "main_category": "Supermarket",
        "rating": 5,
        "reviews": 3,
        "website": "https://www.aeonmaxvalu.com.vn/",
        "phone": "0352 787 486",
        "address": "XQ58+RHW AEON MaxValu La Casta, Khu \u0111\u00f4 th\u1ecb V\u0103n Ph\u00fa, H\u00e0 \u0110\u00f4ng, H\u00e0 N\u1ed9i"
    },
    {
        "title": "MM Mega Market H\u00e0 \u0110\u00f4ng",
        "link": "https://www.google.com/maps/place/MM+Mega+Market+H%C3%A0+%C4%90%C3%B4ng/data=!4m7!3m6!1s0x313452d740805e19:0x6f86ddb54aa66c2a!8m2!3d20.9642345!4d105.7719851!16s%2Fg%2F11bw4pqm08!19sChIJGV6AQNdSNDERKmymSrXdhm8?authuser=0&hl=en&rclk=1",
        "main_category": "Shopping mall",
        "rating": 4.2,
        "reviews": 1278,
        "website": "http://www.mmvietnam.com/",
        "phone": "0943 143 994",
        "address": "MM Mega Market H\u00e0 \u0110\u00f4ng, \u0110. T\u00f4 Hi\u1ec7u, H\u00e0 C\u1ea7u, H\u00e0 \u0110\u00f4ng, H\u00e0 N\u1ed9i 100000"
    },
    {
        "title": "WinMart+",
        "link": "https://www.google.com/maps/place/WinMart%2B/data=!4m7!3m6!1s0x3135acd5a991dceb:0xe4a9728593795959!8m2!3d20.969753!4d105.78514!16s%2Fg%2F11jcfm32wx!19sChIJ69yRqdWsNTERWVl5k4VyqeQ?authuser=0&hl=en&rclk=1",
        "main_category": "Supermarket",
        "rating": 3.3,
        "reviews": 4,
        "website": null,
        "phone": "024 7106 6866",
        "address": "WinMart+, S\u1ed1 1 P. Y\u00ean Ph\u00fac, P. Ph\u00fac La, H\u00e0 \u0110\u00f4ng, H\u00e0 N\u1ed9i 12108"
    },
    {
        "title": "WinMart+",
        "link": "https://www.google.com/maps/place/WinMart%2B/data=!4m7!3m6!1s0x3134532bb5f07d85:0xb170ef2ebeb913bb!8m2!3d20.970194!4d105.7771467!16s%2Fg%2F11jnv4fnnr!19sChIJhX3wtStTNDERuxO5vi7vcLE?authuser=0&hl=en&rclk=1",
        "main_category": "Supermarket",
        "rating": 4,
        "reviews": 25,
        "website": null,
        "phone": "024 7106 6866",
        "address": "WinMart+, S\u1ed1 37 P. L\u00ea L\u1ee3i, P. Nguy\u1ec5n Tr\u00e3i, H\u00e0 \u0110\u00f4ng, H\u00e0 N\u1ed9i 12107"
    },
    {
        "title": "Nh\u00e0 Ph\u00e2n ph\u1ed1i T\u1ea5m \u1ed1p 3D.",
        "link": "https://www.google.com/maps/place/Nh%C3%A0+Ph%C3%A2n+ph%E1%BB%91i+T%E1%BA%A5m+%E1%BB%91p+3D./data=!4m7!3m6!1s0x3135acd2f4d00611:0xdb750d778541f82f!8m2!3d20.9773641!4d105.7848624!16s%2Fg%2F11cr_qytts!19sChIJEQbQ9NKsNTERL_hBhXcNdds?authuser=0&hl=en&rclk=1",
        "main_category": "Supermarket",
        "rating": null,
        "reviews": null,
        "website": null,
        "phone": "0969 557 566",
        "address": "Nh\u00e0 Ph\u00e2n ph\u1ed1i T\u1ea5m \u1ed1p 3D., T\u00f2a n SDU ,143 Tr\u1ea7n Ph\u00fa, H\u00e0, P. V\u0103n Qu\u00e1n, H\u00e0 \u0110\u00f4ng, H\u00e0 N\u1ed9i"
    },
    {
        "title": "\u0110i\u1ec7n M\u00e1y Xanh",
        "link": "https://www.google.com/maps/place/%C4%90i%E1%BB%87n+M%C3%A1y+Xanh/data=!4m7!3m6!1s0x3134530efe68269f:0xea1de6c9e56362f!8m2!3d20.9831231!4d105.7701552!16s%2Fg%2F11j07ndx93!19sChIJnyZo_g5TNDERLzZWnmzeoQ4?authuser=0&hl=en&rclk=1",
        "main_category": "Electronics store",
        "rating": 4.5,
        "reviews": 130,
        "website": "https://www.dienmayxanh.com/?utm_source=GMB_list&utm_medium=organic&utm_campaign=GMB_website",
        "phone": "1800 1061",
        "address": "\u0110i\u1ec7n M\u00e1y Xanh, 194 \u0110\u01b0\u1eddng V\u1ea1n Ph\u00fac, V\u1ea1n Ph\u00fac, H\u00e0 \u0110\u00f4ng, H\u00e0 N\u1ed9i 10000"
    },
    {
        "title": "T Mart",
        "link": "https://www.google.com/maps/place/T+Mart/data=!4m7!3m6!1s0x313452d6d04f12a5:0x59a7cc778ea57586!8m2!3d20.9630223!4d105.7737792!16s%2Fg%2F11d_257f62!19sChIJpRJP0NZSNDERhnWljnfMp1k?authuser=0&hl=en&rclk=1",
        "main_category": "Supermarket",
        "rating": 4,
        "reviews": 16,
        "website": null,
        "phone": "024 7308 3366",
        "address": "T Mart, Chung c\u01b0 CT2 Xu\u00e2n Mai, \u0110. T\u00f4 Hi\u1ec7u, H\u00e0 C\u1ea7u, H\u00e0 \u0110\u00f4ng, H\u00e0 N\u1ed9i"
    },
    {
        "title": "WinMart+",
        "link": "https://www.google.com/maps/place/WinMart%2B/data=!4m7!3m6!1s0x3134531b888b4507:0xe4aa06224d9bbec!8m2!3d20.966314!4d105.775557!16s%2Fg%2F11g6rcj454!19sChIJB0WLiBtTNDER7LvZJGKgSg4?authuser=0&hl=en&rclk=1",
        "main_category": "Supermarket",
        "rating": 4.3,
        "reviews": 45,
        "website": null,
        "phone": "024 7106 6866",
        "address": "WinMart+, L\u00f4 B15, B\u1ed3 H\u1ecfa, H\u00e0 C\u1ea7u, H\u00e0 \u0110\u00f4ng, H\u00e0 N\u1ed9i 12106"
    },
    {
        "title": "B\u1ea3o Nghi Mart",
        "link": "https://www.google.com/maps/place/B%E1%BA%A3o+Nghi+Mart/data=!4m7!3m6!1s0x3135ad598b951505:0xab0f8c51e3bfc282!8m2!3d20.9802799!4d105.783861!16s%2Fg%2F11qq34ggzt!19sChIJBRWVi1mtNTERgsK_41GMD6s?authuser=0&hl=en&rclk=1",
        "main_category": "Supermarket",
        "rating": 5,
        "reviews": 2,
        "website": null,
        "phone": "0902 221 381",
        "address": "B\u1ea3o Nghi Mart, S\u1ed1 17 P. M\u1ed9 Lao, H\u00e0 \u0110\u00f4ng, H\u00e0 N\u1ed9i 100000"
    },
    {
        "title": "HapuMart",
        "link": "https://www.google.com/maps/place/HapuMart/data=!4m7!3m6!1s0x3135ad386d50158b:0x8486bbcc73b625a8!8m2!3d20.9870837!4d105.7829436!16s%2Fg%2F11gy2h7sj0!19sChIJixVQbTitNTERqCW2c8y7hoQ?authuser=0&hl=en&rclk=1",
        "main_category": "Supermarket",
        "rating": 4.8,
        "reviews": 11,
        "website": "https://hapumart.com.vn/",
        "phone": "0902 278 373",
        "address": "HapuMart, 76 li\u1ec1n k\u1ec1, 6A P. Nguy\u1ec5n V\u0103n L\u1ed9c, P. M\u1ed9 Lao, H\u00e0 \u0110\u00f4ng, H\u00e0 N\u1ed9i"
    },
    {
        "title": "Winmart+",
        "link": "https://www.google.com/maps/place/Winmart%2B/data=!4m7!3m6!1s0x3135adfb75162157:0x587c334e9b0a4847!8m2!3d20.9690863!4d105.7907094!16s%2Fg%2F11h84yvmn3!19sChIJVyEWdfutNTERR0gKm04zfFg?authuser=0&hl=en&rclk=1",
        "main_category": "Supermarket",
        "rating": null,
        "reviews": null,
        "website": null,
        "phone": null,
        "address": "Winmart+, 7 \u0110\u01b0\u1eddng TT7, Khu \u0111\u00f4 th\u1ecb V\u0103n Ph\u00fa, H\u00e0 \u0110\u00f4ng, H\u00e0 N\u1ed9i"
    },
    {
        "title": "Si\u00eau th\u1ecb ti\u1ec7n l\u1ee3i TDmart",
        "link": "https://www.google.com/maps/place/Si%C3%AAu+th%E1%BB%8B+ti%E1%BB%87n+l%E1%BB%A3i+TDmart/data=!4m7!3m6!1s0x313453e22e38153d:0xc1ffeb055707f380!8m2!3d20.9580954!4d105.7657836!16s%2Fg%2F11n017q1rn!19sChIJPRU4LuJTNDERgPMHVwXr_8E?authuser=0&hl=en&rclk=1",
        "main_category": "Grocery store",
        "rating": null,
        "reviews": null,
        "website": null,
        "phone": null,
        "address": "Si\u00eau th\u1ecb ti\u1ec7n l\u1ee3i TDmart, s\u1ed1 15 LK 27, Khu \u0111\u00f4 th\u1ecb V\u0103n Ph\u00fa, H\u00e0 \u0110\u00f4ng, H\u00e0 N\u1ed9i"
    },
    {
        "title": "Trung T\u00e2m Tmdv H\u00e0 \u0110\u00f4ng",
        "link": "https://www.google.com/maps/place/Trung+T%C3%A2m+Tmdv+H%C3%A0+%C4%90%C3%B4ng/data=!4m7!3m6!1s0x3134532ae768a2ab:0xc7e4fadbf783305a!8m2!3d20.9699449!4d105.7806864!16s%2Fg%2F1hc5qdnq0!19sChIJq6Jo5ypTNDERWjCD99v65Mc?authuser=0&hl=en&rclk=1",
        "main_category": "Supermarket",
        "rating": 5,
        "reviews": 1,
        "website": null,
        "phone": "024 3338 2446",
        "address": "Trung T\u00e2m Tmdv H\u00e0 \u0110\u00f4ng, 37 B\u00e0 Tri\u1ec7u, P. Nguy\u1ec5n Tr\u00e3i, H\u00e0 \u0110\u00f4ng, H\u00e0 N\u1ed9i"
    },
    {
        "title": "Electric Media Mart supermarket Thanh Xuan",
        "link": "https://www.google.com/maps/place/Electric+Media+Mart+supermarket+Thanh+Xuan/data=!4m7!3m6!1s0x3135acce73f2a2e7:0xbcd84e7c58047a93!8m2!3d20.9802214!4d105.7882601!16s%2Fg%2F12cplnz54!19sChIJ56Lyc86sNTERk3oEWHxO2Lw?authuser=0&hl=en&rclk=1",
        "main_category": "Electronics store",
        "rating": 3.7,
        "reviews": 694,
        "website": "https://mediamart.vn/",
        "phone": "0973 726 969",
        "address": "Electric Media Mart supermarket Thanh Xuan, 131 Tr\u1ea7n Ph\u00fa, P. V\u0103n Qu\u00e1n, H\u00e0 \u0110\u00f4ng, H\u00e0 N\u1ed9i 100000"
    },
    {
        "title": "Boss Store - Si\u00eau Th\u1ecb Ti\u1ec7n \u00cdch",
        "link": "https://www.google.com/maps/place/Boss+Store+-+Si%C3%AAu+Th%E1%BB%8B+Ti%E1%BB%87n+%C3%8Dch/data=!4m7!3m6!1s0x31345360471e5051:0xd5692d19c04ce689!8m2!3d20.9603013!4d105.7657041!16s%2Fg%2F11tjvgz4w8!19sChIJUVAeR2BTNDERieZMwBktadU?authuser=0&hl=en&rclk=1",
        "main_category": "Supermarket",
        "rating": null,
        "reviews": null,
        "website": null,
        "phone": "0703 622 497",
        "address": "Boss Store - Si\u00eau Th\u1ecb Ti\u1ec7n \u00cdch, to\u00e0 La Casta, S\u1ed1 sh21 t\u1ea7ng 1, Khu \u0111\u00f4 th\u1ecb V\u0103n Ph\u00fa, H\u00e0 \u0110\u00f4ng, H\u00e0 N\u1ed9i"
    },
    {
        "title": "Si\u00eau Th\u1ecb Gi\u00e1 T\u1ed1t",
        "link": "https://www.google.com/maps/place/Si%C3%AAu+Th%E1%BB%8B+Gi%C3%A1+T%E1%BB%91t/data=!4m7!3m6!1s0x3135acc565669a9b:0x5cb415a34a30fcfc!8m2!3d20.9800158!4d105.7944304!16s%2Fg%2F11b7ss_g47!19sChIJm5pmZcWsNTER_PwwSqMVtFw?authuser=0&hl=en&rclk=1",
        "main_category": "Grocery store",
        "rating": null,
        "reviews": null,
        "website": null,
        "phone": "0796 003 456",
        "address": "XQJV+2Q3 Si\u00eau Th\u1ecb Gi\u00e1 T\u1ed1t, \u0110\u01b0\u1eddng 19/5, P. V\u0103n Qu\u00e1n, H\u00e0 \u0110\u00f4ng, H\u00e0 N\u1ed9i"
    },
    {
        "title": "H\u1ea3i Nam Co.opmart",
        "link": "https://www.google.com/maps/place/H%E1%BA%A3i+Nam+Co.opmart/data=!4m7!3m6!1s0x3134535ee23e3b55:0xd8b08933516f72e8!8m2!3d20.9564027!4d105.7332045!16s%2Fg%2F11qg27w8j9!19sChIJVTs-4l5TNDER6HJvUTOJsNg?authuser=0&hl=en&rclk=1",
        "main_category": "Supermarket",
        "rating": 4.1,
        "reviews": 7,
        "website": "https://hai-nam-coopmart.business.site/?utm_source=gmb&utm_medium=referral",
        "phone": "0904 632 389",
        "address": "H\u1ea3i Nam Co.opmart, 33 Ng\u00f5 65 Y\u00ean L\u1ed9, Y\u00ean Ngh\u0129a, H\u00e0 \u0110\u00f4ng, H\u00e0 N\u1ed9i"
    },
    {
        "title": "Si\u00eau th\u1ecb m\u00e1y chi\u1ebfu c\u0169",
        "link": "https://www.google.com/maps/place/Si%C3%AAu+th%E1%BB%8B+m%C3%A1y+chi%E1%BA%BFu+c%C5%A9/data=!4m7!3m6!1s0x3134533f9099faa9:0xdbc0f22a333b7231!8m2!3d20.9779822!4d105.7879558!16s%2Fg%2F11g1dqvrrv!19sChIJqfqZkD9TNDERMXI7MyrywNs?authuser=0&hl=en&rclk=1",
        "main_category": "Supermarket",
        "rating": 5,
        "reviews": 1,
        "website": "http://techplaza.vn/",
        "phone": "0936 939 486",
        "address": "Si\u00eau th\u1ecb m\u00e1y chi\u1ebfu c\u0169, 23 Nguy\u1ec5n Khuy\u1ebfn, P. V\u0103n Qu\u00e1n, H\u00e0 \u0110\u00f4ng, H\u00e0 N\u1ed9i 100000"
    },
    {
        "title": "Si\u00eau th\u1ecb Altic Mart",
        "link": "https://www.google.com/maps/place/Si%C3%AAu+th%E1%BB%8B+Altic+Mart/data=!4m7!3m6!1s0x313453b458612ff1:0x9653047fd685cfdf!8m2!3d20.9462104!4d105.7546504!16s%2Fg%2F11j1390gdp!19sChIJ8S9hWLRTNDER38-F1n8EU5Y?authuser=0&hl=en&rclk=1",
        "main_category": "Supermarket",
        "rating": 4.6,
        "reviews": 5,
        "website": null,
        "phone": "0965 230 943",
        "address": "Si\u00eau th\u1ecb Altic Mart, Ki-\u1ed1t 8 t\u00f2a nh\u00e0 V4 khu \u0111\u00f4 th\u1ecb m\u1edbi the Vesta, H\u00e0 \u0110\u00f4ng, H\u00e0 N\u1ed9i"
    },
    {
        "title": "Si\u00eau th\u1ecb \u0110i\u1ec7n m\u00e1y HC - V\u1ea1n Ph\u00fac",
        "link": "https://www.google.com/maps/place/Si%C3%AAu+th%E1%BB%8B+%C4%90i%E1%BB%87n+m%C3%A1y+HC+-+V%E1%BA%A1n+Ph%C3%BAc/data=!4m7!3m6!1s0x3134530fd3c4198d:0x6e44d0b5a99396f4!8m2!3d20.9781445!4d105.7740356!16s%2Fg%2F11j13vtl75!19sChIJjRnE0w9TNDER9JaTqbXQRG4?authuser=0&hl=en&rclk=1",
        "main_category": "Supermarket",
        "rating": 4.1,
        "reviews": 99,
        "website": "http://hc.com.vn/",
        "phone": "1800 1788",
        "address": "Si\u00eau th\u1ecb \u0110i\u1ec7n m\u00e1y HC - V\u1ea1n Ph\u00fac, 63, H\u00e0 \u0110\u00f4ng, H\u00e0 N\u1ed9i"
    },
    {
        "title": "Aeon Mall H\u00e0 \u0110\u00f4ng",
        "link": "https://www.google.com/maps/place/Aeon+Mall+H%C3%A0+%C4%90%C3%B4ng/data=!4m7!3m6!1s0x3135ab7bee9f7757:0x4ebf8ccfc24ec4ae!8m2!3d20.9897037!4d105.7517169!16s%2Fg%2F11hyt9z552!19sChIJV3ef7nurNTERrsROws-Mv04?authuser=0&hl=en&rclk=1",
        "main_category": "Shopping mall",
        "rating": 4.6,
        "reviews": 8290,
        "website": "https://aeonmall-hadong.com.vn/",
        "phone": "024 3757 6999",
        "address": "Aeon Mall H\u00e0 \u0110\u00f4ng, D\u01b0\u01a1ng N\u1ed9i, H\u00e0 \u0110\u00f4ng, H\u00e0 N\u1ed9i"
    },
    {
        "title": "QMart D\u01b0\u01a1ng N\u1ed9i",
        "link": "https://www.google.com/maps/place/QMart+D%C6%B0%C6%A1ng+N%E1%BB%99i/data=!4m7!3m6!1s0x313453b104caacd1:0xeffef8751fd3b83!8m2!3d20.9640395!4d105.7487196!16s%2Fg%2F11gr76ndl2!19sChIJ0azKBLFTNDERgzv9UYfv_w4?authuser=0&hl=en&rclk=1",
        "main_category": "Supermarket",
        "rating": 4,
        "reviews": 4,
        "website": null,
        "phone": null,
        "address": "QMart D\u01b0\u01a1ng N\u1ed9i, HH2 Building, La Kh\u00ea, H\u00e0 \u0110\u00f4ng, H\u00e0 N\u1ed9i"
    },
    {
        "title": "Si\u00eau th\u1ecb \u0111\u1ed3 th\u1ea3 L\u1ea9u Chipmart H\u00e0 \u0110\u00f4ng",
        "link": "https://www.google.com/maps/place/Si%C3%AAu+th%E1%BB%8B+%C4%91%E1%BB%93+th%E1%BA%A3+L%E1%BA%A9u+Chipmart+H%C3%A0+%C4%90%C3%B4ng/data=!4m7!3m6!1s0x3134531c2d5fc5b5:0xe1d581c119947f33!8m2!3d20.9634028!4d105.7673488!16s%2Fg%2F11ks2m9342!19sChIJtcVfLRxTNDERM3-UGcGB1eE?authuser=0&hl=en&rclk=1",
        "main_category": "Store",
        "rating": null,
        "reviews": null,
        "website": null,
        "phone": "0961 286 697",
        "address": "Si\u00eau th\u1ecb \u0111\u1ed3 th\u1ea3 L\u1ea9u Chipmart H\u00e0 \u0110\u00f4ng, 22 P. Tr\u1ea7n \u0110\u0103ng Ninh, Ph\u00fa La, H\u00e0 \u0110\u00f4ng, H\u00e0 N\u1ed9i 12100"
    },
    {
        "title": "AEON MaxValu Hyundai",
        "link": "https://www.google.com/maps/place/AEON+MaxValu+Hyundai/data=!4m7!3m6!1s0x3134536d3716cdd5:0x808a7e8644a50b33!8m2!3d20.9627454!4d105.7754968!16s%2Fg%2F11rgx1ft7s!19sChIJ1c0WN21TNDERMwulRIZ-ioA?authuser=0&hl=en&rclk=1",
        "main_category": "Supermarket",
        "rating": 4.4,
        "reviews": 30,
        "website": "https://www.facebook.com/AeonMaxValu.vn/",
        "phone": "024 2240 8008",
        "address": "XQ7G+35X AEON MaxValu Hyundai, H\u00e0 Tr\u00ec, H\u00e0 \u0110\u00f4ng, H\u00e0 N\u1ed9i 100000"
    },
    {
        "title": "Ti\u1ebfn L\u1ee3i Mart",
        "link": "https://www.google.com/maps/place/Ti%E1%BA%BFn+L%E1%BB%A3i+Mart/data=!4m7!3m6!1s0x3134532168a4b7a7:0x616f0281b636480f!8m2!3d20.9744323!4d105.7626893!16s%2Fg%2F11c2k983tj!19sChIJp7ekaCFTNDERD0g2toECb2E?authuser=0&hl=en&rclk=1",
        "main_category": "Supermarket",
        "rating": 4.1,
        "reviews": 10,
        "website": null,
        "phone": null,
        "address": "XQF7+Q3G Ti\u1ebfn L\u1ee3i Mart, Khu \u0111\u00f4 th\u1ecb V\u0103n Kh\u00ea, H\u00e0 \u0110\u00f4ng, H\u00e0 N\u1ed9i"
    },
    {
        "title": "Supermarket Hien Luong",
        "link": "https://www.google.com/maps/place/Supermarket+Hien+Luong/data=!4m7!3m6!1s0x313452fa0a094d7b:0x793c225326592944!8m2!3d20.959773!4d105.7421531!16s%2Fg%2F11ddxy5yj4!19sChIJe00JCvpSNDERRClZJlMiPHk?authuser=0&hl=en&rclk=1",
        "main_category": "Supermarket",
        "rating": 4.1,
        "reviews": 17,
        "website": "http://shopee.vn/sieuthihienluong",
        "phone": "0984 525 959",
        "address": "Supermarket Hien Luong, Hh2D Khu \u0111\u00f4 th\u1ecb D\u01b0\u01a1ng N\u1ed9i, Y\u00ean Ngh\u0129a, H\u00e0 \u0110\u00f4ng, H\u00e0 N\u1ed9i"
    },
    {
        "title": "Si\u00eau th\u1ecb mini D\u0169ng Xoan",
        "link": "https://www.google.com/maps/place/Si%C3%AAu+th%E1%BB%8B+mini+D%C5%A9ng+Xoan/data=!4m7!3m6!1s0x31345346ddd0e14f:0x4dbf5a37f8f0b692!8m2!3d20.991695!4d105.737349!16s%2Fg%2F11jpblm4qg!19sChIJT-HQ3UZTNDERkrbw-Ddav00?authuser=0&hl=en&rclk=1",
        "main_category": "Supermarket",
        "rating": null,
        "reviews": null,
        "website": null,
        "phone": "0386 856 622",
        "address": "Si\u00eau th\u1ecb mini D\u0169ng Xoan, 47 La D\u01b0\u01a1ng, D\u01b0\u01a1ng N\u1ed9i, H\u00e0 \u0110\u00f4ng, H\u00e0 N\u1ed9i"
    },
    {
        "title": "FHE MART H\u00c0 N\u1ed8I",
        "link": "https://www.google.com/maps/place/FHE+MART+H%C3%80+N%E1%BB%98I/data=!4m7!3m6!1s0x313453c00839b113:0x26064b34ea1f4e6f!8m2!3d20.9809672!4d105.7820419!16s%2Fg%2F11stpknzs2!19sChIJE7E5CMBTNDERb04f6jRLBiY?authuser=0&hl=en&rclk=1",
        "main_category": "Supermarket",
        "rating": null,
        "reviews": null,
        "website": "http://fhe.com.vn/",
        "phone": "0328 219 222",
        "address": "FHE MART H\u00c0 N\u1ed8I, 59 \u0111\u01b0\u1eddng 36M, P. M\u1ed9 Lao, H\u00e0 \u0110\u00f4ng, H\u00e0 N\u1ed9i"
    },
    {
        "title": "Si\u00eau Th\u1ecb H\u00e0n qu\u1ed1c Ch\u00ednh H\u00e3ng -Simoo.com.vn",
        "link": "https://www.google.com/maps/place/Si%C3%AAu+Th%E1%BB%8B+H%C3%A0n+qu%E1%BB%91c+Ch%C3%ADnh+H%C3%A3ng+-Simoo.com.vn/data=!4m7!3m6!1s0x3135abd3d71969f9:0xa546b8da402896e3!8m2!3d20.9509996!4d105.7923317!16s%2Fg%2F11rkn78pdf!19sChIJ-WkZ19OrNTER45YoQNq4RqU?authuser=0&hl=en&rclk=1",
        "main_category": "Supermarket",
        "rating": 5,
        "reviews": 1,
        "website": "https://simoo.com.vn/",
        "phone": "0333 832 296",
        "address": "Si\u00eau Th\u1ecb H\u00e0n qu\u1ed1c Ch\u00ednh H\u00e3ng -Simoo.com.vn, Chung cu Mipec Cty View, H\u00e0 N\u1ed9i 10000"
    },
    {
        "title": "TC Mart Th\u1ebf Gi\u1edbi B\u1ec9m S\u1eefa",
        "link": "https://www.google.com/maps/place/TC+Mart+Th%E1%BA%BF+Gi%E1%BB%9Bi+B%E1%BB%89m+S%E1%BB%AFa/data=!4m7!3m6!1s0x313453a966dc9d23:0x30ade515afc0d9a!8m2!3d20.9597901!4d105.7646261!16s%2Fg%2F11nns9592l!19sChIJI53cZqlTNDERmg38WlHeCgM?authuser=0&hl=en&rclk=1",
        "main_category": "Supermarket",
        "rating": 4,
        "reviews": 2,
        "website": null,
        "phone": "0921 250 258",
        "address": "TC Mart Th\u1ebf Gi\u1edbi B\u1ec9m S\u1eefa, Li\u1ec1n K\u1ec1 10, Khu \u0110\u00f4 Th\u1ecb M\u1edbi V\u0103n Ph\u00fa, 16, Ph\u00fa La, H\u00e0 \u0110\u00f4ng, H\u00e0 N\u1ed9i"
    },
    {
        "title": "Si\u00eau th\u1ecb Ho\u00e0ng Anh",
        "link": "https://www.google.com/maps/place/Si%C3%AAu+th%E1%BB%8B+Ho%C3%A0ng+Anh/data=!4m7!3m6!1s0x313453a2ec6c12a3:0x142bfc29eea7aea0!8m2!3d20.9549677!4d105.7442689!16s%2Fg%2F11lgx4r5gh!19sChIJoxJs7KJTNDERoK6n7in8KxQ?authuser=0&hl=en&rclk=1",
        "main_category": "Supermarket",
        "rating": 4,
        "reviews": 1,
        "website": null,
        "phone": "0945 353 000",
        "address": "Si\u00eau th\u1ecb Ho\u00e0ng Anh, CT2, t\u00f2a nh\u00e0 B\u1ed9 T\u01b0 L\u1ec7nh Th\u1ee7 \u0110\u00f4, Y\u00ean Ngh\u0129a, H\u00e0 \u0110\u00f4ng, H\u00e0 N\u1ed9i"
    },
    {
        "title": "Nhi Mart",
        "link": "https://www.google.com/maps/place/Nhi+Mart/data=!4m7!3m6!1s0x313453a0d246fc79:0x1f4ee81b734468d!8m2!3d20.9677!4d105.7726779!16s%2Fg%2F11s84k9t67!19sChIJefxG0qBTNDERjUY0t4Hu9AE?authuser=0&hl=en&rclk=1",
        "main_category": "Supermarket",
        "rating": null,
        "reviews": null,
        "website": null,
        "phone": "0835 384 891",
        "address": "Nhi Mart, Ng\u00f5 3 Khu C\u1ea7u \u0110\u01a1 5, P. Quang Trung, H\u00e0 \u0110\u00f4ng, H\u00e0 N\u1ed9i"
    },
    {
        "title": "T - Mart",
        "link": "https://www.google.com/maps/place/T+-+Mart/data=!4m7!3m6!1s0x3135adb2d4f852c5:0x97329c8d738454a3!8m2!3d20.9615461!4d105.7959014!16s%2Fg%2F11h07y2rfg!19sChIJxVL41LKtNTERo1SEc42cMpc?authuser=0&hl=en&rclk=1",
        "main_category": "Supermarket",
        "rating": 3.3,
        "reviews": 6,
        "website": null,
        "phone": null,
        "address": "T - Mart, Chung C\u01b0 Hemisco, To\u00e0, XaLa, H\u00e0 \u0110\u00f4ng, H\u00e0 N\u1ed9i"
    },
    {
        "title": "VinMart+",
        "link": "https://www.google.com/maps/place/VinMart%2B/data=!4m7!3m6!1s0x313452f342b8c999:0xb3b60f834a7927e6!8m2!3d20.9495203!4d105.7418299!16s%2Fg%2F11jp93nf23!19sChIJmcm4QvNSNDER5id5SoMPtrM?authuser=0&hl=en&rclk=1",
        "main_category": "Supermarket",
        "rating": 4.2,
        "reviews": 19,
        "website": null,
        "phone": "024 7106 6866",
        "address": "VinMart+, 42 \u0110\u01b0\u1eddng Ngh\u0129a L\u1ed9, Y\u00ean Ngh\u0129a, H\u00e0 \u0110\u00f4ng, H\u00e0 N\u1ed9i 12116"
    },
    {
        "title": "SI\u00caU TH\u1eca \u0110\u1ed2NG H\u1ed2 - H\u00c0 \u0110\u00d4NG",
        "link": "https://www.google.com/maps/place/SI%C3%8AU+TH%E1%BB%8A+%C4%90%E1%BB%92NG+H%E1%BB%92+-+H%C3%80+%C4%90%C3%94NG/data=!4m7!3m6!1s0x3134532e3bbdac81:0x330831da7d5fb87a!8m2!3d20.9662232!4d105.7695357!16s%2Fg%2F11s0tlwk2p!19sChIJgay9Oy5TNDERerhffdoxCDM?authuser=0&hl=en&rclk=1",
        "main_category": "Watch store",
        "rating": null,
        "reviews": null,
        "website": null,
        "phone": "024 3556 8555",
        "address": "SI\u00caU TH\u1eca \u0110\u1ed2NG H\u1ed2 - H\u00c0 \u0110\u00d4NG, 208 \u0110. Quang Trung, H\u00e0 C\u1ea7u, H\u00e0 \u0110\u00f4ng, H\u00e0 N\u1ed9i 10000"
    },
    {
        "title": "Si\u00eau Th\u1ecb Miniti Mart 10K",
        "link": "https://www.google.com/maps/place/Si%C3%AAu+Th%E1%BB%8B+Miniti+Mart+10K/data=!4m7!3m6!1s0x3135adbad4effc5f:0x10f7be1c18bebdb8!8m2!3d20.9666677!4d105.7824812!16s%2Fg%2F11fp1n5tf7!19sChIJX_zv1LqtNTERuL2-GBy-9xA?authuser=0&hl=en&rclk=1",
        "main_category": "Home goods store",
        "rating": 4.6,
        "reviews": 5,
        "website": null,
        "phone": "0986 773 499",
        "address": "Si\u00eau Th\u1ecb Miniti Mart 10K, 112 B\u00e0 Tri\u1ec7u, H\u00e0 C\u1ea7u, H\u00e0 \u0110\u00f4ng, H\u00e0 N\u1ed9i"
    },
    {
        "title": "Kyotosho - Si\u00eau th\u1ecb h\u00e0ng Nh\u1eadt n\u1ed9i \u0111\u1ecba",
        "link": "https://www.google.com/maps/place/Kyotosho+-+Si%C3%AAu+th%E1%BB%8B+h%C3%A0ng+Nh%E1%BA%ADt+n%E1%BB%99i+%C4%91%E1%BB%8Ba/data=!4m7!3m6!1s0x3135ada6339d788d:0x27ca2232df6c640!8m2!3d20.9894569!4d105.7996709!16s%2Fg%2F11fmpydk05!19sChIJjXidM6atNTERQMb2LSOifAI?authuser=0&hl=en&rclk=1",
        "main_category": "Supermarket",
        "rating": 4.6,
        "reviews": 17,
        "website": null,
        "phone": "0972 264 588",
        "address": "Kyotosho - Si\u00eau th\u1ecb h\u00e0ng Nh\u1eadt n\u1ed9i \u0111\u1ecba, 612 \u0110. Nguy\u1ec5n Tr\u00e3i, Thanh Xu\u00e2n B\u1eafc, H\u00e0 \u0110\u00f4ng, H\u00e0 N\u1ed9i"
    },
    {
        "title": "si\u00eau th\u1ecb xa la",
        "link": "https://www.google.com/maps/place/si%C3%AAu+th%E1%BB%8B+xa+la/data=!4m7!3m6!1s0x3135ad28f9f078e3:0xef3eb8e847982944!8m2!3d20.9634534!4d105.7915592!16s%2Fg%2F11cpg70375!19sChIJ43jw-SitNTERRCmYR-i4Pu8?authuser=0&hl=en&rclk=1",
        "main_category": "Shopping mall",
        "rating": 3.9,
        "reviews": 10,
        "website": null,
        "phone": "0343 242 432",
        "address": "XQ7R+9JM si\u00eau th\u1ecb xa la, P. Ph\u00fac La, H\u00e0 \u0110\u00f4ng, H\u00e0 N\u1ed9i"
    },
    {
        "title": "Terra Mart",
        "link": "https://www.google.com/maps/place/Terra+Mart/data=!4m7!3m6!1s0x3134533d42d54e93:0x7d685dead0d6cc52!8m2!3d20.9570538!4d105.7373449!16s%2Fg%2F11s9c0vl1q!19sChIJk07VQj1TNDERUszW0OpdaH0?authuser=0&hl=en&rclk=1",
        "main_category": "Supermarket",
        "rating": null,
        "reviews": null,
        "website": null,
        "phone": "0913 221 182",
        "address": "Terra Mart, U8-L44, K\u0110T \u0110\u00f4 Ngh\u0129a, H\u00e0 \u0110\u00f4ng, H\u00e0 N\u1ed9i"
    },
    {
        "title": "HaHa Mart",
        "link": "https://www.google.com/maps/place/HaHa+Mart/data=!4m7!3m6!1s0x31345316fd7be563:0x6c10d7158c683736!8m2!3d20.982798!4d105.7673369!16s%2Fg%2F11f5lq37p0!19sChIJY-V7_RZTNDERNjdojBXXEGw?authuser=0&hl=en&rclk=1",
        "main_category": "Grocery store",
        "rating": 3.8,
        "reviews": 9,
        "website": null,
        "phone": "0902 165 799",
        "address": "HaHa Mart, 22 LK4, Ti\u1ec3u khu \u0110\u00f4 th\u1ecb m\u1edbi, H\u00e0 \u0110\u00f4ng, H\u00e0 N\u1ed9i 10000"
    },
    {
        "title": "Si\u00eau th\u1ecb m\u1eb9 b\u1ea7u v\u00e0 em b\u00e9 KidsPlaza 66 Nguy\u1ec5n Khuy\u1ebfn - H\u00e0 \u0110\u00f4ng",
        "link": "https://www.google.com/maps/place/Si%C3%AAu+th%E1%BB%8B+m%E1%BA%B9+b%E1%BA%A7u+v%C3%A0+em+b%C3%A9+KidsPlaza+66+Nguy%E1%BB%85n+Khuy%E1%BA%BFn+-+H%C3%A0+%C4%90%C3%B4ng/data=!4m7!3m6!1s0x3135acd18b59bfd1:0x1fa5e9320a91e7af!8m2!3d20.9769198!4d105.7881591!16s%2Fg%2F11btrs6dpz!19sChIJ0b9Zi9GsNTERr-eRCjLppR8?authuser=0&hl=en&rclk=1",
        "main_category": "Baby store",
        "rating": 4.1,
        "reviews": 119,
        "website": "http://www.kidsplaza.vn/",
        "phone": "024 3312 0224",
        "address": "Si\u00eau th\u1ecb m\u1eb9 b\u1ea7u v\u00e0 em b\u00e9 KidsPlaza 66 Nguy\u1ec5n Khuy\u1ebfn - H\u00e0 \u0110\u00f4ng, 66 Nguy\u1ec5n Khuy\u1ebfn, P. V\u0103n Qu\u00e1n, H\u00e0 \u0110\u00f4ng, H\u00e0 N\u1ed9i 100000"
    },
    {
        "title": "Oma Mart (Organic Mart)",
        "link": "https://www.google.com/maps/place/Oma+Mart+%28Organic+Mart%29/data=!4m7!3m6!1s0x3135ad84b8ffa2b1:0x99a0d97126fa29a4!8m2!3d20.9796683!4d105.7956757!16s%2Fg%2F11rqvvw03k!19sChIJsaL_uIStNTERpCn6JnHZoJk?authuser=0&hl=en&rclk=1",
        "main_category": "Supermarket",
        "rating": 5,
        "reviews": 4,
        "website": "https://omamart.vn/",
        "phone": "0961 316 123",
        "address": "Oma Mart (Organic Mart), Ng\u00f5 143 Chi\u1ebfn Th\u1eafng, P. V\u0103n Qu\u00e1n, H\u00e0 \u0110\u00f4ng, H\u00e0 N\u1ed9i 100000"
    },
    {
        "title": "Si\u00eau Th\u1ecb \u0110i\u1ec7n M\u00e1y Pico",
        "link": "https://www.google.com/maps/place/Si%C3%AAu+Th%E1%BB%8B+%C4%90i%E1%BB%87n+M%C3%A1y+Pico/data=!4m7!3m6!1s0x3135acd4c2fa4c33:0xdde2b11e109a7189!8m2!3d20.9707685!4d105.7837214!16s%2Fg%2F11g01vp8p2!19sChIJM0z6wtSsNTERiXGaEB6x4t0?authuser=0&hl=en&rclk=1",
        "main_category": "Hypermarket",
        "rating": 4.1,
        "reviews": 201,
        "website": "https://pico.vn/",
        "phone": "1900 6619",
        "address": "Si\u00eau Th\u1ecb \u0110i\u1ec7n M\u00e1y Pico, 38 Ph\u00f9ng H\u01b0ng (m\u1edbi, P. Ph\u00fac La, H\u00e0 \u0110\u00f4ng, H\u00e0 N\u1ed9i 100000"
    },
    {
        "title": "Si\u00eau th\u1ecb \u0110i\u1ec7n m\u00e1y Xanh - Quang Trung (Ba La), H\u00e0 \u0110\u00f4ng",
        "link": "https://www.google.com/maps/place/Si%C3%AAu+th%E1%BB%8B+%C4%90i%E1%BB%87n+m%C3%A1y+Xanh+-+Quang+Trung+%28Ba+La%29,+H%C3%A0+%C4%90%C3%B4ng/data=!4m7!3m6!1s0x313452e83e1e4939:0xb0bf52e752c4f2c1!8m2!3d20.9597565!4d105.7619789!16s%2Fg%2F11c1tm5h2l!19sChIJOUkePuhSNDERwfLEUudSv7A?authuser=0&hl=en&rclk=1",
        "main_category": "Electronics store",
        "rating": 4.2,
        "reviews": 175,
        "website": "https://www.dienmayxanh.com/?utm_source=GMB_list&utm_medium=organic&utm_campaign=GMB_website",
        "phone": "1800 1061",
        "address": "Si\u00eau th\u1ecb \u0110i\u1ec7n m\u00e1y Xanh - Quang Trung (Ba La), H\u00e0 \u0110\u00f4ng, 748 \u0110. Quang Trung, P. Quang Trung, H\u00e0 \u0110\u00f4ng, H\u00e0 N\u1ed9i 10000"
    },
    {
        "title": "Si\u00eau Th\u1ecb \u0110i\u1ec7n M\u00e1y Pico",
        "link": "https://www.google.com/maps/place/Si%C3%AAu+Th%E1%BB%8B+%C4%90i%E1%BB%87n+M%C3%A1y+Pico/data=!4m7!3m6!1s0x3135adf10a4c3c99:0xc271c0661521d900!8m2!3d20.9512118!4d105.7912296!16s%2Fg%2F11h3bms5wl!19sChIJmTxMCvGtNTERANkhFWbAccI?authuser=0&hl=en&rclk=1",
        "main_category": "Hypermarket",
        "rating": 4,
        "reviews": 29,
        "website": "https://pico.vn/",
        "phone": "1900 6619",
        "address": "Si\u00eau Th\u1ecb \u0110i\u1ec7n M\u00e1y Pico, P. Ho\u00e0ng C\u00f4ng, Ki\u1ebfn H\u01b0ng, H\u00e0 \u0110\u00f4ng, H\u00e0 N\u1ed9i 100000"
    },
    {
        "title": "\u0110i\u1ec7n m\u00e1y xanh Ba la",
        "link": "https://www.google.com/maps/place/%C4%90i%E1%BB%87n+m%C3%A1y+xanh+Ba+la/data=!4m7!3m6!1s0x313452e819f8d6f9:0xca6522772cf0165f!8m2!3d20.9570158!4d105.7577297!16s%2Fg%2F11gff8cq8f!19sChIJ-db4GehSNDERXxbwLHciZco?authuser=0&hl=en&rclk=1",
        "main_category": "Supermarket",
        "rating": 4.4,
        "reviews": 59,
        "website": "https://www.dienmayxanh.com/dien-may-746-748-750-752-quang-trung-pphu-la-qha-dong-tpha-noi-328",
        "phone": null,
        "address": "\u0110i\u1ec7n m\u00e1y xanh Ba la, 746 \u0110. Quang Trung, La Kh\u00ea, H\u00e0 \u0110\u00f4ng, H\u00e0 N\u1ed9i"
    },
    {
        "title": "ANMAI.STORE",
        "link": "https://www.google.com/maps/place/ANMAI.STORE/data=!4m7!3m6!1s0x3135ad53cdbe92b9:0x867cf6390c71974!8m2!3d20.9471417!4d105.7851661!16s%2Fg%2F11skd2f1fd!19sChIJuZK-zVOtNTERdBnHkGPPZwg?authuser=0&hl=en&rclk=1",
        "main_category": "Supermarket",
        "rating": null,
        "reviews": null,
        "website": null,
        "phone": null,
        "address": "ANMAI.STORE, t\u00f2a 3, Khu nh\u00e0 \u1edf H\u01b0ng Th\u1ecbnh, H\u00e0 \u0110\u00f4ng, H\u00e0 N\u1ed9i"
    },
    {
        "title": "Hay Ho Mart",
        "link": "https://www.google.com/maps/place/Hay+Ho+Mart/data=!4m7!3m6!1s0x313453056013a5df:0xfac5a661119bc437!8m2!3d20.9663919!4d105.7794345!16s%2Fg%2F11fdwzc_q6!19sChIJ36UTYAVTNDERN8SbEWGmxfo?authuser=0&hl=en&rclk=1",
        "main_category": "Supermarket",
        "rating": 5,
        "reviews": 3,
        "website": null,
        "phone": "0904 696 493",
        "address": "Hay Ho Mart, L\u00f4 12 li\u1ec1n k\u1ec1, 29 P. H\u00e0 Tr\u00ec, H\u00e0 C\u1ea7u, H\u00e0 \u0110\u00f4ng, H\u00e0 N\u1ed9i 12106"
    },
    {
        "title": "Asia Mart",
        "link": "https://www.google.com/maps/place/Asia+Mart/data=!4m7!3m6!1s0x31345380d791a3eb:0xffd5ed97a479d817!8m2!3d20.9575446!4d105.7686481!16s%2Fg%2F11h10znn76!19sChIJ66OR14BTNDERF9h5pJft1f8?authuser=0&hl=en&rclk=1",
        "main_category": "Chinese supermarket",
        "rating": null,
        "reviews": null,
        "website": null,
        "phone": "024 6666 3027",
        "address": "Asia Mart, 357 Lacasta,V\u0103n Ph\u00fa, Ph\u00fa La, H\u00e0 \u0110\u00f4ng, H\u00e0 N\u1ed9i"
    },
    {
        "title": "\u0110i\u1ec7n M\u00e1y Aeon H\u00e0 \u0110\u00f4ng",
        "link": "https://www.google.com/maps/place/%C4%90i%E1%BB%87n+M%C3%A1y+Aeon+H%C3%A0+%C4%90%C3%B4ng/data=!4m7!3m6!1s0x313453934ed93349:0xb7ade2093b89ddcc!8m2!3d20.9904156!4d105.7522065!16s%2Fg%2F11j3bgvm8x!19sChIJSTPZTpNTNDERzN2JOwnirbc?authuser=0&hl=en&rclk=1",
        "main_category": "Electronics store",
        "rating": 4.6,
        "reviews": 1194,
        "website": "https://aeoneshop.com/",
        "phone": "024 2220 8788",
        "address": "\u0110i\u1ec7n M\u00e1y Aeon H\u00e0 \u0110\u00f4ng, T\u1ed5 d\u00e2n ph\u1ed1 Ho\u00e0ng V\u0103n Th\u1ee5, D\u01b0\u01a1ng N\u1ed9i, H\u00e0 \u0110\u00f4ng, H\u00e0 N\u1ed9i"
    },
    {
        "title": "Si\u00eau th\u1ecb Duy Duy\u00ean +++ X\u1ed5 s\u1ed1 Vietlot ++ R\u00fat ti\u1ec1n nhanh \ud83c\udfe7 + Tr\u00e0 \u0111\u00e1 ch\u00e9n gi\u00f3...",
        "link": "https://www.google.com/maps/place/Si%C3%AAu+th%E1%BB%8B+Duy+Duy%C3%AAn+%2B%2B%2B+X%E1%BB%95+s%E1%BB%91+Vietlot+%2B%2B+R%C3%BAt+ti%E1%BB%81n+nhanh+%F0%9F%8F%A7+%2B+Tr%C3%A0+%C4%91%C3%A1+ch%C3%A9n+gi%C3%B3.../data=!4m7!3m6!1s0x3134532495b4d1d9:0x79d1bc15c2f48d4e!8m2!3d20.939126!4d105.7547316!16s%2Fg%2F11t0_qlkrf!19sChIJ2dG0lSRTNDERTo30whW80Xk?authuser=0&hl=en&rclk=1",
        "main_category": "Grocery store",
        "rating": 4.9,
        "reviews": 176,
        "website": null,
        "phone": "0374 546 028",
        "address": "Si\u00eau th\u1ecb Duy Duy\u00ean +++ X\u1ed5 s\u1ed1 Vietlot ++ R\u00fat ti\u1ec1n nhanh \ud83c\udfe7 + Tr\u00e0 \u0111\u00e1 ch\u00e9n gi\u00f3..., T\u1ed5 7 \u0110. Huy\u1ec1n K\u1ef3, Nh\u00e0 30, H\u00e0 \u0110\u00f4ng, H\u00e0 N\u1ed9i"
    },
    {
        "title": "\u0110i\u1ec7n m\u00e1y Nguy\u1ec5n Kim Tr\u1ea7n Ph\u00fa, H\u00e0 \u0110\u00f4ng",
        "link": "https://www.google.com/maps/place/%C4%90i%E1%BB%87n+m%C3%A1y+Nguy%E1%BB%85n+Kim+Tr%E1%BA%A7n+Ph%C3%BA,+H%C3%A0+%C4%90%C3%B4ng/data=!4m7!3m6!1s0x3135accee60a1f8b:0x4feae691fbf11f77!8m2!3d20.9795!4d105.7874372!16s%2Fg%2F11btrs75x_!19sChIJix8K5s6sNTERdx_x-5Hm6k8?authuser=0&hl=en&rclk=1",
        "main_category": "Electronics store",
        "rating": 3.9,
        "reviews": 555,
        "website": "https://www.nguyenkim.com//?utm_source=google&utm_campaign%20=&utm_medium=GMB-NK%20Ha%20Dong",
        "phone": "1800 6800",
        "address": "\u0110i\u1ec7n m\u00e1y Nguy\u1ec5n Kim Tr\u1ea7n Ph\u00fa, H\u00e0 \u0110\u00f4ng, 135 Tr\u1ea7n Ph\u00fa, P. V\u0103n Qu\u00e1n, H\u00e0 \u0110\u00f4ng, H\u00e0 N\u1ed9i"
    },
    {
        "title": "Si\u00eau Th\u1ecb \u0110i\u1ec7n M\u00e1y Pico",
        "link": "https://www.google.com/maps/place/Si%C3%AAu+Th%E1%BB%8B+%C4%90i%E1%BB%87n+M%C3%A1y+Pico/data=!4m7!3m6!1s0x3134532a0e36d99b:0x7c8eea1e9cd5de5c!8m2!3d20.9533376!4d105.7525113!16s%2Fg%2F11gy571x7y!19sChIJm9k2DipTNDERXN7VnB7qjnw?authuser=0&hl=en&rclk=1",
        "main_category": "Supermarket",
        "rating": 4.3,
        "reviews": 62,
        "website": "https://pico.vn/",
        "phone": "1900 6619",
        "address": "Si\u00eau Th\u1ecb \u0110i\u1ec7n M\u00e1y Pico, 944 \u0110. Quang Trung, Ph\u00fa L\u00e2m, H\u00e0 \u0110\u00f4ng, H\u00e0 N\u1ed9i 100000"
    },
    {
        "title": "Si\u00eau th\u1ecb \u0110i\u1ec7n m\u00e1y XANH Quang Trung, H\u00e0 \u0110\u00f4ng",
        "link": "https://www.google.com/maps/place/Si%C3%AAu+th%E1%BB%8B+%C4%90i%E1%BB%87n+m%C3%A1y+XANH+Quang+Trung,+H%C3%A0+%C4%90%C3%B4ng/data=!4m7!3m6!1s0x31345328add38c23:0xf5bc297bf0f15e08!8m2!3d20.9623721!4d105.7643319!16s%2Fg%2F11h8bn022m!19sChIJI4zTrShTNDERCF7x8HspvPU?authuser=0&hl=en&rclk=1",
        "main_category": "Electronics store",
        "rating": 4.8,
        "reviews": 36,
        "website": "https://www.dienmayxanh.com/?utm_source=GMB_list&utm_medium=organic&utm_campaign=GMB_website",
        "phone": "1800 1061",
        "address": "Si\u00eau th\u1ecb \u0110i\u1ec7n m\u00e1y XANH Quang Trung, H\u00e0 \u0110\u00f4ng, 418 \u0110. Quang Trung, La Kh\u00ea, H\u00e0 \u0110\u00f4ng, H\u00e0 N\u1ed9i 10000"
    },
    {
        "title": "Chinese Supermarket, Tangren Supermarket",
        "link": "https://www.google.com/maps/place/Chinese+Supermarket,+Tangren+Supermarket/data=!4m7!3m6!1s0x3134534fd22c402f:0x4196b430b1d96b85!8m2!3d20.9629444!4d105.7629013!16s%2Fg%2F11twjmx5yq!19sChIJL0As0k9TNDERhWvZsTC0lkE?authuser=0&hl=en&rclk=1",
        "main_category": "Supermarket",
        "rating": 5,
        "reviews": 3,
        "website": null,
        "phone": null,
        "address": "Chinese Supermarket, Tangren Supermarket, 29 \u0110. L\u00ea Tr\u1ecdng T\u1ea5n, La Kh\u00ea, H\u00e0 \u0110\u00f4ng, H\u00e0 N\u1ed9i 100000"
    },
    {
        "title": "TinMart Chi Nh\u00e1nh Quang Trung - C\u1eeda H\u00e0ng Ti\u1ec7n L\u1ee3i",
        "link": "https://www.google.com/maps/place/TinMart+Chi+Nh%C3%A1nh+Quang+Trung+-+C%E1%BB%ADa+H%C3%A0ng+Ti%E1%BB%87n+L%E1%BB%A3i/data=!4m7!3m6!1s0x3134532b0bb8e0df:0x1fa10c34632aa1dc!8m2!3d20.956268!4d105.7567586!16s%2Fg%2F11td11k596!19sChIJ3-C4CytTNDER3KEqYzQMoR8?authuser=0&hl=en&rclk=1",
        "main_category": "Convenience store",
        "rating": 5,
        "reviews": 4,
        "website": "http://tinnhatminh.com/",
        "phone": "0398 215 218",
        "address": "TinMart Chi Nh\u00e1nh Quang Trung - C\u1eeda H\u00e0ng Ti\u1ec7n L\u1ee3i, 812 \u0110. Quang Trung, La Kh\u00ea, H\u00e0 \u0110\u00f4ng, H\u00e0 N\u1ed9i 100000"
    },
    {
        "title": "Sakuko Store V\u0103n Ph\u00fa",
        "link": "https://www.google.com/maps/place/Sakuko+Store+V%C4%83n+Ph%C3%BA/data=!4m7!3m6!1s0x313452dbdf54708d:0x1d1abf3db51b07ac!8m2!3d20.957936!4d105.767868!16s%2Fg%2F11f5dscgtm!19sChIJjXBU39tSNDERrAcbtT2_Gh0?authuser=0&hl=en&rclk=1",
        "main_category": "Supermarket",
        "rating": 4.2,
        "reviews": 45,
        "website": "http://sakukostore.com.vn/",
        "phone": "024 6686 0888",
        "address": "Sakuko Store V\u0103n Ph\u00fa, 252 Lacasta, Khu \u0111\u00f4 th\u1ecb V\u0103n Ph\u00fa, H\u00e0 \u0110\u00f4ng, H\u00e0 N\u1ed9i"
    },
    {
        "title": "\u0110i\u1ec7n M\u00e1y Xanh",
        "link": "https://www.google.com/maps/place/%C4%90i%E1%BB%87n+M%C3%A1y+Xanh/data=!4m7!3m6!1s0x3135acd28b922b2d:0x992318e16a1f31ad!8m2!3d20.979417!4d105.7854803!16s%2Fg%2F11xm04dqt!19sChIJLSuSi9KsNTERrTEfauEYI5k?authuser=0&hl=en&rclk=1",
        "main_category": "Electronics store",
        "rating": 4.1,
        "reviews": 267,
        "website": "https://www.dienmayxanh.com/?utm_source=GMB_list&utm_medium=organic&utm_campaign=GMB_website",
        "phone": "1800 1061",
        "address": "\u0110i\u1ec7n M\u00e1y Xanh, 110 Tr\u1ea7n Ph\u00fa, Khu \u0111\u00f4 th\u1ecb M\u1ed7 Lao, H\u00e0 \u0110\u00f4ng, H\u00e0 N\u1ed9i 10000"
    },
    {
        "title": "T-Mart CT1",
        "link": "https://www.google.com/maps/place/T-Mart+CT1/data=!4m7!3m6!1s0x3135ad28a63182d5:0xaa15f94df9e8be86!8m2!3d20.9604832!4d105.794537!16s%2Fg%2F11bccm64xp!19sChIJ1YIxpiitNTERhr7o-U35Fao?authuser=0&hl=en&rclk=1",
        "main_category": "Grocery store",
        "rating": 3.6,
        "reviews": 15,
        "website": null,
        "phone": null,
        "address": "T-Mart CT1, CT1 Nam, Xa La, H\u00e0 \u0110\u00f4ng, H\u00e0 N\u1ed9i"
    },
    {
        "title": "Si\u00eau Th\u1ecb Tinh D\u1ea7u 100",
        "link": "https://www.google.com/maps/place/Si%C3%AAu+Th%E1%BB%8B+Tinh+D%E1%BA%A7u+100/data=!4m7!3m6!1s0x3135acd4c12739c1:0x75bca5ae138a0508!8m2!3d20.9716135!4d105.7833227!16s%2Fg%2F11btrs1htq!19sChIJwTknwdSsNTERCAWKE66lvHU?authuser=0&hl=en&rclk=1",
        "main_category": "Grocery store",
        "rating": 2.5,
        "reviews": 2,
        "website": null,
        "phone": "0934 663 338",
        "address": "Si\u00eau Th\u1ecb Tinh D\u1ea7u 100, 3 \u0110. Ph\u00f9ng H\u01b0ng, P. Ph\u00fac La, H\u00e0 \u0110\u00f4ng, H\u00e0 N\u1ed9i"
    },
    {
        "title": "C\u1eeda H\u00e0ng Mini Mart",
        "link": "https://www.google.com/maps/place/C%E1%BB%ADa+H%C3%A0ng+Mini+Mart/data=!4m7!3m6!1s0x3135accdbbfc3eb3:0x730957dd5f36c113!8m2!3d20.9801161!4d105.7866932!16s%2Fg%2F11q7gmljl7!19sChIJsz78u82sNTERE8E2X91XCXM?authuser=0&hl=en&rclk=1",
        "main_category": "Department store",
        "rating": null,
        "reviews": null,
        "website": null,
        "phone": "0975 790 692",
        "address": "C\u1eeda H\u00e0ng Mini Mart, LK, 26 P. Nguy\u1ec5n V\u0103n Tr\u1ed7i, P. M\u1ed9 Lao, H\u00e0 \u0110\u00f4ng, H\u00e0 N\u1ed9i"
    }
]